meta_json/__init__.py
meta_json/attribute_parser.py
meta_json/layer_parser.py
meta_json/meta_json.py
meta_json/type_parser.py
tests/__init__.py
tests/integration/__init__.py
tests/integration/test_meta_json.py
tests/unit/__init__.py
tests/unit/test_meta_json.py
tests/unit/test_meta_json_parser.py
meta_json-1.0.0.dist-info/METADATA
meta_json-1.0.0.dist-info/WHEEL
meta_json-1.0.0.dist-info/top_level.txt
meta_json-1.0.0.dist-info/zip-safe
meta_json-1.0.0.dist-info/RECORD
