Metadata-Version: 2.1
Name: meta_json
Version: 1.0.0
Summary: Extract metadata from a deserialized JSON.
Home-page: https://github.com/juangcr/meta_json
Author: Juan Cortés
Author-email: Juan Cortés <juang.cortes@outlook.com>
License: BSD 3-Clause License
Project-URL: Repository, https://github.com/juangcr/meta_json
Keywords: metadata,json
Classifier: Development Status :: 4 - Beta
Classifier: License :: OSI Approved :: BSD License
Classifier: Programming Language :: Python :: 3.8
Classifier: Programming Language :: Python :: 3.9
Classifier: Programming Language :: Python :: 3.10
Classifier: Programming Language :: Python :: 3.11
Classifier: Programming Language :: Python :: 3.12
Classifier: Operating System :: OS Independent
Requires-Python: >=3.8
Provides-Extra: test
Requires-Dist: coverage ; extra == 'test'
Requires-Dist: pytest ; extra == 'test'
Requires-Dist: black ; extra == 'test'
Requires-Dist: flake8 ; extra == 'test'
Requires-Dist: mypy ; extra == 'test'
